pyhurl/__init__.py
pyhurl/llm_client.py
pyhurl/log_factory.py
pyhurl/mysql_client.py
pyhurl/oss_client.py
pyhurl/sqlite_client.py
pyhurl-1.1.0.dist-info/licenses/LICENSE
pyhurl-1.1.0.dist-info/METADATA
pyhurl-1.1.0.dist-info/WHEEL
pyhurl-1.1.0.dist-info/top_level.txt
pyhurl-1.1.0.dist-info/RECORD
