Metadata-Version: 2.4
Name: pyhurl
Version: 1.1.0
Summary: A set of useful functions that I use in projects.
Author-email: Rongliang Hu <hurongliang@gmail.com>
License: MIT
Project-URL: Homepage, https://github.com/hurongliang/pyhurl
Requires-Python: >=3.8
License-File: LICENSE
Requires-Dist: python-dotenv
Provides-Extra: mysql
Requires-Dist: pymysql; extra == "mysql"
Provides-Extra: oss
Requires-Dist: oss2; extra == "oss"
Provides-Extra: llm
Requires-Dist: openai; extra == "llm"
Requires-Dist: ollama; extra == "llm"
Provides-Extra: all
Requires-Dist: oss2; extra == "all"
Requires-Dist: openai; extra == "all"
Requires-Dist: ollama; extra == "all"
Dynamic: license-file
